ieee_papers_mapper/__init__.py
ieee_papers_mapper/main.py
ieee_papers_mapper/app/__init__.py
ieee_papers_mapper/app/callbacks.py
ieee_papers_mapper/app/dash_webapp.py
ieee_papers_mapper/data/__init__.py
ieee_papers_mapper/data/classify_papers.py
ieee_papers_mapper/data/database.py
ieee_papers_mapper/data/get_papers.py
ieee_papers_mapper/data/pipeline.py
ieee_papers_mapper/data/process_papers.py
ieee_papers_mapper-1.0.0.dist-info/LICENSE
ieee_papers_mapper-1.0.0.dist-info/METADATA
ieee_papers_mapper-1.0.0.dist-info/WHEEL
ieee_papers_mapper-1.0.0.dist-info/top_level.txt
ieee_papers_mapper-1.0.0.dist-info/RECORD
