Metadata-Version: 2.1
Name: ieee_papers_mapper
Version: 1.0.0
Summary: A project for fetching, processing, and classifying IEEE papers.
Home-page: https://github.com/alex-anast/ieee-papers-mapper
Author: Alexandros Anastasiou
Author-email: anastasioyaa@gmail.com
Classifier: Programming Language :: Python :: 3
Classifier: License :: OSI Approved :: MIT License
Classifier: Operating System :: POSIX :: Linux
Requires-Python: >=3.12
License-File: LICENSE
Requires-Dist: dash
Requires-Dist: pandas
Requires-Dist: dotenv
Requires-Dist: python-dotenv
Requires-Dist: transformers
Requires-Dist: torch
Requires-Dist: torchvision
Requires-Dist: torchaudio
Requires-Dist: sympy
Requires-Dist: pillow
Requires-Dist: networkx
Requires-Dist: mpmath
Requires-Dist: APScheduler
